filldocx/__init__.py
filldocx-1.0.1.dist-info/METADATA
filldocx-1.0.1.dist-info/WHEEL
filldocx-1.0.1.dist-info/top_level.txt
filldocx-1.0.1.dist-info/RECORD
